LICENSE
README.md
pyproject.toml
openpilot_logging/__init__.py
openpilot_logging/api.py
openpilot_logging/auth_config.py
openpilot_logging/azure_container.py
openpilot_logging/comma_car_segments.py
openpilot_logging/file_helpers.py
openpilot_logging/filereader.py
openpilot_logging/helpers.py
openpilot_logging/hw.py
openpilot_logging/logreader.py
openpilot_logging/openpilotci.py
openpilot_logging/openpilotcontainers.py
openpilot_logging/route.py
openpilot_logging/url_file.py
openpilot_logging.egg-info/PKG-INFO
openpilot_logging.egg-info/SOURCES.txt
openpilot_logging.egg-info/dependency_links.txt
openpilot_logging.egg-info/requires.txt
openpilot_logging.egg-info/top_level.txt
openpilot_logging/cereal/__init__.py
openpilot_logging/cereal/car.capnp
openpilot_logging/cereal/custom.capnp
openpilot_logging/cereal/legacy.capnp
openpilot_logging/cereal/log.capnp
openpilot_logging/cereal/include/c++.capnp