Metadata-Version: 2.2
Name: openpilot-logging
Version: 0.1.5
Summary: Tools to read openpilot logs
Author-email: Vehicle Researcher <user@comma.ai>
License: Copyright (c) 2020, Comma.ai, Inc.
Project-URL: homepage, https://github.com/commaai/openpilot
Requires-Python: <3.13,>=3.9
License-File: LICENSE
Requires-Dist: requests
Requires-Dist: tqdm
Requires-Dist: pycapnp
Requires-Dist: setuptools
Requires-Dist: zstandard
Provides-Extra: testing
Requires-Dist: ruff; extra == "testing"
Requires-Dist: pytest; extra == "testing"
Requires-Dist: pytest-mock; extra == "testing"
Requires-Dist: pytest-xdist; extra == "testing"
Requires-Dist: pytest-subtests; extra == "testing"
Requires-Dist: hypothesis==6.47.*; extra == "testing"
Requires-Dist: parameterized<0.9,>=0.8; extra == "testing"
Requires-Dist: pre-commit; extra == "testing"
Provides-Extra: docs
Requires-Dist: Jinja2; extra == "docs"
Requires-Dist: natsort; extra == "docs"
Provides-Extra: examples
Requires-Dist: inputs; extra == "examples"
Requires-Dist: matplotlib; extra == "examples"
